savis/__init__.py
savis/attention.py
savis/generator.py
savis/visualization.py
savis-0.4.3.dist-info/METADATA
savis-0.4.3.dist-info/WHEEL
savis-0.4.3.dist-info/licenses/LICENSE
savis-0.4.3.dist-info/RECORD
