Metadata-Version: 2.4
Name: savis
Version: 0.4.3
Summary: A sentence-level visualization tool for attention in large language models
Project-URL: Homepage, https://github.com/Seongbuming/savis
Project-URL: Repository, https://github.com/Seongbuming/savis
Project-URL: Documentation, https://github.com/Seongbuming/savis#readme
Project-URL: Bug Tracker, https://github.com/Seongbuming/savis/issues
Author-email: Seongbum Seo <seo@seongbum.com>
License: Copyright (c) 2012-2024 Scott Chacon and others
License-File: LICENSE
Keywords: attention,large language models,nlp,visualization
Classifier: Development Status :: 4 - Beta
Classifier: Intended Audience :: Developers
Classifier: Intended Audience :: Science/Research
Classifier: License :: OSI Approved :: MIT License
Classifier: Programming Language :: Python
Classifier: Programming Language :: Python :: 3
Classifier: Topic :: Scientific/Engineering :: Artificial Intelligence
Classifier: Topic :: Software Development :: Libraries :: Python Modules
Requires-Python: >=3.10
Requires-Dist: matplotlib
Requires-Dist: nltk
Requires-Dist: numpy
Requires-Dist: torch
Requires-Dist: transformers
